{"generatedAt":"2026-07-08T17:27:57+02:00","checkpoints":[{"name":"login","status":"baseline","score":null},{"name":"header","status":"baseline","score":null},{"name":"footer","status":"baseline","score":null},{"name":"giftcard","status":"baseline","score":null},{"name":"cms-cookies","status":"baseline","score":null},{"name":"brands","status":"baseline","score":null},{"name":"licences","status":"baseline","score":null},{"name":"cms-contact","status":"baseline","score":null},{"name":"cms-livraison","status":"baseline","score":null},{"name":"product-preorder-actions","status":"baseline","score":null},{"name":"product-preorder-viewport","status":"baseline","score":null},{"name":"product-stock-actions","status":"baseline","score":null},{"name":"product-stock-viewport","status":"baseline","score":null}]}